statebot/__init__.py
statebot/skeleton.py
statebot-0.0.0.dist-info/LICENSE.txt
statebot-0.0.0.dist-info/METADATA
statebot-0.0.0.dist-info/WHEEL
statebot-0.0.0.dist-info/top_level.txt
statebot-0.0.0.dist-info/RECORD
